ComplexJSON/__init__.py
ComplexJSON/complexJSONDecoder.py
ComplexJSON/complexJSONEncoder.py
ComplexJSON/funcdef.py
ComplexJSON/jsondef.py
ComplexJSON/vardef.py
ComplexJSON-1.2.0.dist-info/LICENSE
ComplexJSON-1.2.0.dist-info/METADATA
ComplexJSON-1.2.0.dist-info/WHEEL
ComplexJSON-1.2.0.dist-info/top_level.txt
ComplexJSON-1.2.0.dist-info/RECORD
